setup.py
yinan_dl/__init__.py
yinan_dl.egg-info/PKG-INFO
yinan_dl.egg-info/SOURCES.txt
yinan_dl.egg-info/dependency_links.txt
yinan_dl.egg-info/not-zip-safe
yinan_dl.egg-info/top_level.txt