Metadata-Version: 1.0
Name: yinan-dl
Version: 0.1
Summary: clinical trial information retriver
Home-page: http://github.com/tongling/clinicaltrial
Author: Yinan Xu
Author-email: yinanxu@wezhuiyi.com
License: MIT
Platform: UNKNOWN
